json2any_plugin/AbstractDataProvider.py
json2any_plugin/AbstractHelperProvider.py
json2any_plugin/AbstractProvider.py
json2any_plugin/AbstractTemplateProvider.py
json2any_plugin/__init__.py
json2any_plugin-1.1.0.dist-info/METADATA
json2any_plugin-1.1.0.dist-info/WHEEL
json2any_plugin-1.1.0.dist-info/RECORD
