Metadata-Version: 2.4
Name: json2any-plugin
Version: 1.1.0
Summary: Json2Any plugin interfaces
Author-email: Maciej Matuszak <maciej.matuszak@gmail.com>
License-Expression: MIT
Requires-Python: >=3.8
Requires-Dist: jinja2>=3.1.6
